osrs_net/__init__.py
osrs_net/grandexchange.py
osrs_net/item.py
osrs_net/hiscores/__init__.py
osrs_net/hiscores/account.py
osrs_net/hiscores/lookup.py
osrs_net/hiscores/skill.py
osrs_net/hiscores/stat.py
osrs_net/resources/items.json
osrs_net/util/__init__.py
osrs_net/util/file_io.py
osrs_net/util/item_scrape.py
osrs_net-0.2.0.dist-info/licenses/LICENSE
osrs_net-0.2.0.dist-info/METADATA
osrs_net-0.2.0.dist-info/WHEEL
osrs_net-0.2.0.dist-info/top_level.txt
osrs_net-0.2.0.dist-info/RECORD
